<?xml version="1.0" encoding="UTF-8"?>
<objects serializationModel="Studio.01.10.00">
    <object class="AudioFile" id="{760c5e5c-32d4-4db5-bfec-703a633ad2c4}">
        <property name="assetPath">
            <value>SOUND_PIXEL_AMBIANCE_GAME.mp3</value>
        </property>
        <property name="isStreaming">
            <value>true</value>
        </property>
        <property name="frequencyInKHz">
            <value>44.0999985</value>
        </property>
        <property name="channelCount">
            <value>2</value>
        </property>
        <property name="length">
            <value>299.07591836734696</value>
        </property>
        <relationship name="masterAssetFolder">
            <destination>{471cbe65-6aed-4780-93c1-fd819d94d313}</destination>
        </relationship>
    </object>
</objects>
